Metadata-Version: 2.1
Name: gptmypr
Version: 0.1.0
Summary: CLI tool that uses OpenAI's GPT to change your code according to comments in the GitHub pull request
Home-page: https://github.com/waclawthedev/GPTmyPR
Author: waclawthedev
Author-email: waclawthedev@gmail.com
License: MIT
Keywords: gptmypr,pull request,code review,refactoring,code quality,ChatGPT,GPT,OpenAI,GitHub
License-File: LICENSE
Requires-Dist: rich==13.7.0
Requires-Dist: openai==1.9.0
Requires-Dist: PyGithub==2.1.1
Requires-Dist: GitPython==3.1.41
